avatars/__init__.py
avatars/api.py
avatars/base_client.py
avatars/client.py
avatars/client_config.py
avatars/config.py
avatars/constants.py
avatars/crash_handler.py
avatars/data_upload.py
avatars/file_downloader.py
avatars/job_launcher.py
avatars/log.py
avatars/manager.py
avatars/models.py
avatars/results_organizer.py
avatars/runner.py
avatars/storage.py
avatars/utils.py
avatars/lib/__init__.py
avatars/lib/continuous_threshold.py
avatars/lib/saferound.py
avatars/lib/split_columns_types.py
avatars/processors/__init__.py
avatars/processors/datetime.py
avatars/processors/expected_mean.py
avatars/processors/geolocation_normalization.py
avatars/processors/group_modalities.py
avatars/processors/inter_record_bounded_cumulated_difference.py
avatars/processors/inter_record_bounded_range_difference.py
avatars/processors/inter_record_cumulated_difference.py
avatars/processors/inter_record_range_difference.py
avatars/processors/perturbation.py
avatars/processors/proportions.py
avatars/processors/relative_difference.py
avatars/processors/to_categorical.py
octopize_avatar-1.15.0.dist-info/METADATA
octopize_avatar-1.15.0.dist-info/WHEEL
octopize_avatar-1.15.0.dist-info/RECORD
