Metadata-Version: 2.4
Name: octopize.avatar
Version: 1.15.0
Summary: Python client for Octopize's avatar API
Author-email: Octopize <pypi-octopize@octopize.io>
License-Expression: Apache-2.0
Requires-Python: >=3.12
Requires-Dist: aiobotocore<=2.22.0
Requires-Dist: botocore<=1.40.17
Requires-Dist: fsspec>=2024.12.0
Requires-Dist: httpx>=0.28.1
Requires-Dist: ipython>=9.2.0
Requires-Dist: octopize-avatar-yaml==0.1.29
Requires-Dist: pandas>=2.3.1
Requires-Dist: pydantic-settings>=2.7.0
Requires-Dist: pydantic>=2.10.4
Requires-Dist: pyyaml>=6.0.2
Requires-Dist: s3fs>=2024.12.0
Requires-Dist: structlog>=24.4.0
Requires-Dist: tenacity>=9.0.0
Requires-Dist: toolz>=1.0.0
Requires-Dist: typer>=0.15.1
